Rocket_Tadj_007/init.py
Rocket_Tadj_007/rocket.py
Rocket_Tadj_007-1.0.0.dist-info/METADATA
Rocket_Tadj_007-1.0.0.dist-info/WHEEL
Rocket_Tadj_007-1.0.0.dist-info/top_level.txt
Rocket_Tadj_007-1.0.0.dist-info/RECORD
