Metadata-Version: 2.1
Name: Rocket_Tadj_007
Version: 1.0.0
Summary: An awesome package that does something
Home-page: http://pypi.python.org/pypi/Rocket_Tadj_007/
Author: walid
Author-email: mw.tadj@esi-sba.dz
License: LICENSE.txt
Requires-Dist: Rocket-Tadj-007
